agl_anonymizer/__init__.py
agl_anonymizer/admin.py
agl_anonymizer/apps.py
agl_anonymizer/asgi.py
agl_anonymizer/models/frozen_east_text_detection.pb
agl_anonymizer/models.py
agl_anonymizer/serializers.py
agl_anonymizer/settings.py
agl_anonymizer/tests.py
agl_anonymizer/urls.py
agl_anonymizer/views.py
agl_anonymizer/wsgi.py
agl_anonymizer-0.1.1.dist-info/METADATA
agl_anonymizer-0.1.1.dist-info/WHEEL
agl_anonymizer-0.1.1.dist-info/RECORD
