Metadata-Version: 2.1
Name: agl_anonymizer
Version: 0.1.1
Summary: This package is made to censor sensitive data in images and extract the contents. NER is planned for the future
License: MIT
Author: maxhild
Author-email: 58726316+maxhild@users.noreply.github.com
Requires-Python: >=3.11,<4.0
Classifier: License :: OSI Approved :: MIT License
Classifier: Programming Language :: Python :: 3
Classifier: Programming Language :: Python :: 3.11
Classifier: Programming Language :: Python :: 3.12
Requires-Dist: Pillow (>=9.0.0,<10.0.0)
Requires-Dist: PyMuPDF (>=1.20.0,<2.0.0)
Requires-Dist: PyPDF2 (==3.0.1)
Requires-Dist: agl-anonymizer-pipeline (>=0.1.2,<0.2.0)
Requires-Dist: django (>=4.2,<4.3)
Requires-Dist: django-bootstrap5 (>=23.4,<24.0)
Requires-Dist: djangorestframework (>=3.14.0,<4.0.0)
Requires-Dist: flair (==0.13.0)
Requires-Dist: gender-guesser (==0.4.0)
Requires-Dist: gensim (>=4.1.2,<5.0.0)
Requires-Dist: gunicorn (>=22.0.0,<23.0.0)
Requires-Dist: numpy (==1.26.4)
Requires-Dist: opencv-python-headless (>=4.10.0.84,<5.0.0.0)
Requires-Dist: reportlab (==4.1.0)
Requires-Dist: requests (==2.31.0)
Requires-Dist: spacy (>=3.4.0,<4.0.0)
Requires-Dist: torch (>=2.2.2,<3.0.0)
Requires-Dist: transformers (>=4.20.0,<5.0.0)
